jak_python_package/__init__.py
jak_python_package/api.py
jak_python_package/edit_message.py
jak_python_package/mathematics.py
beast_night_tv-2.0.3.dist-info/LICENSE.txt
beast_night_tv-2.0.3.dist-info/METADATA
beast_night_tv-2.0.3.dist-info/WHEEL
beast_night_tv-2.0.3.dist-info/top_level.txt
beast_night_tv-2.0.3.dist-info/RECORD
