Metadata-Version: 2.1
Name: beast-night-tv
Version: 2.0.3
Summary: A Python Package made by JAK!!
Home-page: https://github.com/Jonak-Adipta-Kalita/JAK-Python-Package
Author: JAK (Jonak Adipta Kalita)
Author-email: <jonakadiptakalita@gmail.com>
License: UNKNOWN
Keywords: python,first_package,edit_message
Platform: UNKNOWN
Classifier: Development Status :: 1 - Planning
Classifier: Natural Language :: English
Classifier: Operating System :: OS Independent
Classifier: Intended Audience :: Developers
Classifier: Programming Language :: Python :: 3
